rspyredis/__init__.py
rspyredis/config.py
rspyredis/connection.py
rspyredis-0.1.2.dist-info/METADATA
rspyredis-0.1.2.dist-info/WHEEL
rspyredis-0.1.2.dist-info/RECORD
