Metadata-Version: 2.3
Name: rspyredis
Version: 0.1.2
Summary: A light python package for redis management.
License: MIT
Author: Reza Shirazi
Author-email: itreza7@gmail.com
Requires-Python: >=3.11,<4.0
Classifier: License :: OSI Approved :: MIT License
Classifier: Programming Language :: Python :: 3
Classifier: Programming Language :: Python :: 3.11
Classifier: Programming Language :: Python :: 3.12
Classifier: Programming Language :: Python :: 3.13
Requires-Dist: redis (>=5.2.1,<6.0.0)
Project-URL: Repository, https://github.com/itreza7/rspyredis
